validation_mcp/__init__.py
validation_mcp/__main__.py
validation_mcp/server.py
validation_mcp/prompts/__init__.py
validation_mcp/prompts/encoding_helper.py
validation_mcp/prompts/security_audit.py
validation_mcp/prompts/validation_workflow.py
validation_mcp/resources/__init__.py
validation_mcp/resources/eip55.py
validation_mcp/resources/patterns.py
validation_mcp/resources/secp256k1.py
validation_mcp/resources/selectors_db.py
validation_mcp/tools/__init__.py
validation_mcp/tools/address_validation.py
validation_mcp/tools/checksum.py
validation_mcp/tools/derivation.py
validation_mcp/tools/hashing.py
validation_mcp/tools/hex_validation.py
validation_mcp/tools/key_validation.py
validation_mcp/tools/selectors.py
validation_mcp/tools/signature_validation.py
validation_mcp/tools/storage.py
validation_mcp_server-1.0.0.dist-info/METADATA
validation_mcp_server-1.0.0.dist-info/WHEEL
validation_mcp_server-1.0.0.dist-info/entry_points.txt
validation_mcp_server-1.0.0.dist-info/RECORD
