Metadata-Version: 2.4
Name: validation-mcp-server
Version: 1.0.0
Summary: MCP server for Ethereum address/key validation and cryptographic utilities
Project-URL: Homepage, https://github.com/nirholas/ethereum-wallet-toolkit
Project-URL: Repository, https://github.com/nirholas/ethereum-wallet-toolkit/tree/main/validation-mcp-server
Project-URL: Documentation, https://github.com/nirholas/ethereum-wallet-toolkit/blob/main/validation-mcp-server/README.md
Author-email: nirholas <nich@ethereum.tools>
License-Expression: MIT
Keywords: checksum,eip55,ethereum,mcp,validation
Classifier: Development Status :: 4 - Beta
Classifier: Intended Audience :: Developers
Classifier: License :: OSI Approved :: MIT License
Classifier: Programming Language :: Python :: 3
Classifier: Programming Language :: Python :: 3.11
Classifier: Programming Language :: Python :: 3.12
Requires-Python: >=3.11
Requires-Dist: eth-account>=0.10.0
Requires-Dist: eth-hash[pycryptodome]>=0.5.0
Requires-Dist: eth-keys>=0.5.0
Requires-Dist: eth-utils>=2.0.0
Requires-Dist: mcp>=1.0.0
Requires-Dist: pydantic>=2.0.0
Provides-Extra: dev
Requires-Dist: pytest-asyncio>=0.21.0; extra == 'dev'
Requires-Dist: pytest>=7.0.0; extra == 'dev'
